brief_excel/__init__.py
brief_excel/module.py
brief_excel-1.0.0.dist-info/licenses/LICENSE
brief_excel-1.0.0.dist-info/METADATA
brief_excel-1.0.0.dist-info/WHEEL
brief_excel-1.0.0.dist-info/top_level.txt
brief_excel-1.0.0.dist-info/RECORD
