Metadata-Version: 2.4
Name: brief-excel
Version: 1.0.0
Summary: 一个强大的Excel处理工具包
Author-email: hh66dw <hh66dw@163.com>
License: MIT License
Project-URL: Homepage, https://gitee.com/hh66dw/brief_excel
Project-URL: Documentation, https://gitee.com/hh66dw/brief_excel#readme
Project-URL: Repository, https://gitee.com/hh66dw/brief_excel
Project-URL: Issues, https://gitee.com/hh66dw/brief_excel/issues
Classifier: Development Status :: 4 - Beta
Classifier: Intended Audience :: Developers
Classifier: License :: OSI Approved :: MIT License
Classifier: Programming Language :: Python :: 3
Classifier: Programming Language :: Python :: 3.7
Classifier: Programming Language :: Python :: 3.8
Classifier: Programming Language :: Python :: 3.9
Classifier: Programming Language :: Python :: 3.10
Classifier: Programming Language :: Python :: 3.11
Classifier: Topic :: Office/Business :: Financial :: Spreadsheet
Classifier: Topic :: Software Development :: Libraries :: Python Modules
Requires-Python: >=3.7
License-File: LICENSE
Requires-Dist: et_xmlfile==2.0.0
Requires-Dist: openpyxl==3.1.5
Requires-Dist: Pillow>=10.0.0
Requires-Dist: requests>=2.31.0
Provides-Extra: dev
Requires-Dist: pytest>=6.0; extra == "dev"
Requires-Dist: pytest-cov>=2.0; extra == "dev"
Requires-Dist: black>=22.0; extra == "dev"
Requires-Dist: flake8>=4.0; extra == "dev"
Requires-Dist: isort>=5.0; extra == "dev"
Dynamic: license-file
